{"total_mbtiles_unicos":39,"visibilidad":{"cur3d":{"cantidad":39,"mbtiles":[{"id":1,"categoria":{"id":1,"nombre":"Fotografías aéreas","visibilidad":["cur3d","mapa_interactivo"]},"nombre":"Foto aérea CABA 1940","url":"https://vectortiles.usig.buenosaires.gob.ar/aereas/fotografias_aereas_1940_caba_3857/","anio":1940,"tipo":"aerea","origen_datos":"sin_dato","autogenerado":null,"fuente":"","frontend_config":{},"timestamp_modificacion":"2022-09-16T21:47:24.776556"},{"id":2,"categoria":{"id":1,"nombre":"Fotografías aéreas","visibilidad":["cur3d","mapa_interactivo"]},"nombre":"Foto aérea CABA 1965","url":"https://vectortiles.usig.buenosaires.gob.ar/aereas/fotografias_aereas_1965_caba_3857/","anio":1965,"tipo":"","origen_datos":"sin_dato","autogenerado":null,"fuente":"","frontend_config":{},"timestamp_modificacion":"2022-09-16T21:50:10.521334"},{"id":3,"categoria":{"id":1,"nombre":"Fotografías aéreas","visibilidad":["cur3d","mapa_interactivo"]},"nombre":"Foto aérea CABA 1978","url":"https://vectortiles.usig.buenosaires.gob.ar/aereas/fotografias_aereas_1978_caba_3857/","anio":1978,"tipo":"","origen_datos":"sin_dato","autogenerado":null,"fuente":"","frontend_config":{},"timestamp_modificacion":"2022-09-16T21:51:17.211397"},{"id":4,"categoria":{"id":1,"nombre":"Fotografías aéreas","visibilidad":["cur3d","mapa_interactivo"]},"nombre":"Foto aérea CABA 2017","url":"https://vectortiles.usig.buenosaires.gob.ar/aereas/fotografias_aereas_2017_caba_3857/","anio":2017,"tipo":"","origen_datos":"sin_dato","autogenerado":null,"fuente":"","frontend_config":{},"timestamp_modificacion":"2022-09-16T21:52:17.428125"},{"id":5,"categoria":{"id":2,"nombre":"Imágenes satelitales","visibilidad":["cur3d","mapa_interactivo"]},"nombre":"Imagen satelital CABA 2004","url":"https://vectortiles.usig.buenosaires.gob.ar/satelitales/imagen_satelital_2004_caba_3857/","anio":2004,"tipo":"","origen_datos":"sin_dato","autogenerado":null,"fuente":"","frontend_config":{},"timestamp_modificacion":"2022-09-16T21:57:08.243587"},{"id":6,"categoria":{"id":2,"nombre":"Imágenes satelitales","visibilidad":["cur3d","mapa_interactivo"]},"nombre":"Imagen satelital CABA 2006","url":"https://vectortiles.usig.buenosaires.gob.ar/satelitales/imagen_satelital_2006_caba_3857/","anio":2006,"tipo":"","origen_datos":"sin_dato","autogenerado":null,"fuente":"","frontend_config":{},"timestamp_modificacion":"2022-09-16T21:58:03.284819"},{"id":7,"categoria":{"id":2,"nombre":"Imágenes satelitales","visibilidad":["cur3d","mapa_interactivo"]},"nombre":"Imagen satelital CABA 2008","url":"https://vectortiles.usig.buenosaires.gob.ar/satelitales/imagen_satelital_2008_caba_3857/","anio":2008,"tipo":"","origen_datos":"sin_dato","autogenerado":null,"fuente":"","frontend_config":{},"timestamp_modificacion":"2022-09-16T22:00:05.826981"},{"id":8,"categoria":{"id":2,"nombre":"Imágenes satelitales","visibilidad":["cur3d","mapa_interactivo"]},"nombre":"Imagen satelital CABA 2009","url":"https://vectortiles.usig.buenosaires.gob.ar/satelitales/imagen_satelital_2009_caba_3857/","anio":2009,"tipo":"","origen_datos":"sin_dato","autogenerado":null,"fuente":"","frontend_config":{},"timestamp_modificacion":"2022-09-16T22:01:19.365765"},{"id":10,"categoria":{"id":3,"nombre":"Franja edificable","visibilidad":["cur3d"]},"nombre":"Línea oficial","url":"https://vectortiles.usig.buenosaires.gob.ar/cur3d/linea_oficial/","anio":2022,"tipo":"","origen_datos":"algoritmos_motor_reglas","autogenerado":null,"fuente":"","frontend_config":{"id":"linea_oficial","info":"Línea que deslinda el lote de la vía pública actual o la línea señalada por el Gobierno para la futura vía pública.","link":"https://data.buenosaires.gob.ar/dataset/linea-oficial","type":"vectortile","color":"#e76056","title":"Línea oficial","options":{"type":"line","paint":{"line-color":"#e76056","line-width":4},"layout":{"visibility":"none"},"source":{"type":"vector","tiles":["https://vectortiles.usig.buenosaires.gob.ar/cur3d/linea_oficial/{z}/{x}/{y}.pbf?optimize=true"],"cluster":false,"maxzoom":18,"minzoom":10},"source-layer":"default"},"displayPopup":false,"popupContent":""},"timestamp_modificacion":"2022-09-19T12:54:16.343143"},{"id":11,"categoria":{"id":3,"nombre":"Franja edificable","visibilidad":["cur3d"]},"nombre":"Líneas Internas de Basamento (L.I.B)","url":"https://vectortiles.usig.buenosaires.gob.ar/cur3d/lib/","anio":2022,"tipo":"","origen_datos":"algoritmos_motor_reglas","autogenerado":null,"fuente":"PDI","frontend_config":{"id":"lib","info":"Traza del plano que limita la edificación permitida del basamento con el Centro Libre de Manzana.","link":"https://data.buenosaires.gob.ar/dataset/franja-edificable-lineas","type":"vectortile","color":"#f3a32d","title":"Líneas Internas de Basamento (L.I.B)","options":{"type":"line","paint":{"line-color":"#f3a32d","line-width":4},"layout":{"visibility":"none"},"source":{"type":"vector","tiles":["https://vectortiles.usig.buenosaires.gob.ar/cur3d/lib/{z}/{x}/{y}.pbf?optimize=true"],"cluster":false,"maxzoom":18,"minzoom":10},"source-layer":"default"},"displayPopup":false,"popupContent":""},"timestamp_modificacion":"2022-09-19T12:55:48.010157"},{"id":12,"categoria":{"id":3,"nombre":"Franja edificable","visibilidad":["cur3d"]},"nombre":"Líneas de Frente Interno (L.F.I)","url":"https://vectortiles.usig.buenosaires.gob.ar/cur3d/lfi/","anio":2022,"tipo":"","origen_datos":"algoritmos_motor_reglas","autogenerado":null,"fuente":"PDI","frontend_config":{"id":"lfi","info":"Es la línea coincidente con la proyección de los planos que determinan el Centro Libre de Manzana. Se sitúa paralelamente con respecto a cada línea oficial a una distancia igual a un cuarto (¼) de la medida entre los puntos medios de las líneas oficiales opuestas de la manzana.","link":"https://data.buenosaires.gob.ar/dataset/franja-edificable-lineas","type":"vectortile","color":"#0389d1","title":"Líneas de Frente Interno (L.F.I)","options":{"type":"line","paint":{"line-color":"#0389d1","line-width":4},"layout":{"visibility":"none"},"source":{"type":"vector","tiles":["https://vectortiles.usig.buenosaires.gob.ar/cur3d/lfi/{z}/{x}/{y}.pbf?optimize=true"],"cluster":false,"maxzoom":18,"minzoom":10},"source-layer":"default"},"displayPopup":false,"popupContent":""},"timestamp_modificacion":"2022-09-19T12:57:17.757380"},{"id":13,"categoria":{"id":3,"nombre":"Franja edificable","visibilidad":["cur3d"]},"nombre":"Banda Mínima Edificable","url":"https://vectortiles.usig.buenosaires.gob.ar/cur3d/banda_minima/","anio":2022,"tipo":"","origen_datos":"algoritmos_motor_reglas","autogenerado":null,"fuente":"PDI","frontend_config":{"id":"banda_minima","info":"La banda edificable es la franja que queda comprendida desde la  línea oficial hasta la línea de frente interno o línea interna de basamento según corresponda y determina el área donde puede edificarse dentro de un lote. En todos los casos se garantiza a las parcelas o lotes una banda edificable mínima de dieciséis (16) metros.","link":"https://data.buenosaires.gob.ar/dataset/banda-minima-edificable","type":"vectortile","color":"#2ebc98","title":"Banda Mínima Edificable","options":{"type":"fill","paint":{"fill-color":"#2ebc98","fill-opacity":0.7},"layout":{"visibility":"none"},"source":{"type":"vector","tiles":["https://vectortiles.usig.buenosaires.gob.ar/cur3d/banda_minima/{z}/{x}/{y}.pbf?optimize=true"],"cluster":false,"maxzoom":18,"minzoom":10},"source-layer":"default"},"displayPopup":false,"popupContent":""},"timestamp_modificacion":"2022-09-19T12:58:41.146876"},{"id":15,"categoria":{"id":3,"nombre":"Franja edificable","visibilidad":["cur3d"]},"nombre":"Unidades de edificabilidad","url":"https://vectortiles.usig.buenosaires.gob.ar/cur3d/volumen_edif/","anio":2022,"tipo":"","origen_datos":"algoritmos_motor_reglas","autogenerado":null,"fuente":"PDI","frontend_config":{"id":"volumen_edif_unidades","info":"Corresponde a la clasificación de las alturas de conformidad al Código Urbanístico.","link":"https://data.buenosaires.gob.ar/dataset/codigo-urbanistico","type":"vectortile","color":"#19c3e3","index":3,"title":"Unidades de edificabilidad","options":{"type":"fill-extrusion","paint":{"fill-extrusion-color":["match",["get","edificabil"],"USAB0","#f3d30c","USAB1","#f0e6cc","USAB2","#c9c2ab","USAM","#f5c294","USAA","#ea9e82","CM","#85adb1","CA","#557e8d","#CCADAD"],"fill-extrusion-height":["get","altura_fin"],"fill-extrusion-opacity":0.8},"filter":["any",["==","edificabil","USAB0"],["==","edificabil","USAB1"],["==","edificabil","USAB2"],["==","edificabil","USAM"],["==","edificabil","USAA"],["==","edificabil","CM"],["==","edificabil","CA"]],"layout":{"visibility":"none"},"source":{"type":"vector","tiles":["https://vectortiles.usig.buenosaires.gob.ar/cur3d/volumen_edif/{z}/{x}/{y}.pbf?optimize=true"],"cluster":false,"maxzoom":18,"minzoom":10},"source-layer":"default"},"reference":[{"id":"highCorridors","color":"#557e8d","subTitle":"38 m"},{"id":"memdiumCorridors","color":"#85adb1","subTitle":"31.2 m"},{"id":"highSustainability","color":"#ea9e82","subTitle":"22.8 m"},{"id":"mediumSustainability","color":"#f5c294","subTitle":"17.2 m"},{"id":"lowSustainability2","color":"#c9c2ab","subTitle":"14.6 m"},{"id":"lowSustainability1","color":"#f0e6cc","subTitle":"12 m"},{"id":"lowSustainability0","color":"#f3d30c","subTitle":"9 m"}],"displayPopup":false,"popupContent":""},"timestamp_modificacion":"2025-04-10T14:32:53.977420"},{"id":16,"categoria":{"id":3,"nombre":"Franja edificable","visibilidad":["cur3d"]},"nombre":"Areas Especiales Individualizadas","url":"https://vectortiles.usig.buenosaires.gob.ar/cur3d/volumen_edif/","anio":2022,"tipo":"","origen_datos":"algoritmos_motor_reglas","autogenerado":null,"fuente":"PDI","frontend_config":{"id":"areas_especiales_individualizadas","info":"Corresponde a la clasificación de las alturas de conformidad al Código Urbanístico.","link":"https://data.buenosaires.gob.ar/dataset/codigo-urbanistico","type":"vectortile","color":"rgb(249, 188, 180)","index":3,"title":"Areas Especiales Individualizadas","options":{"type":"fill-extrusion","paint":{"fill-extrusion-color":["match",["get","origen"],"APH","rgb(249, 188, 180)","U","rgb(209, 187, 208)","white"],"fill-extrusion-height":["get","altura_fin"],"fill-extrusion-opacity":0.8},"filter":["any",["==","origen","APH"],["==","origen","U"]],"layout":{"visibility":"none"},"source":{"type":"vector","tiles":["https://vectortiles.usig.buenosaires.gob.ar/cur3d/volumen_edif/{z}/{x}/{y}.pbf?optimize=true"],"cluster":false,"maxzoom":18,"minzoom":10},"source-layer":"default"},"reference":[{"id":"APH","color":"rgb(249, 188, 180)","subTitle":"APH"},{"id":"U","color":"rgb(209, 187, 208)","subTitle":"U"}],"displayPopup":false,"popupContent":""},"timestamp_modificacion":"2022-09-19T13:04:08.645105"},{"id":17,"categoria":{"id":3,"nombre":"Franja edificable","visibilidad":["cur3d"]},"nombre":"Superficie edificable en planta (pisada)","url":"https://vectortiles.usig.buenosaires.gob.ar/cur3d/volumen_edif/","anio":2022,"tipo":"","origen_datos":"algoritmos_motor_reglas","autogenerado":null,"fuente":"PDI","frontend_config":{"id":"volumen_edif_basamento","info":"Es el área correspondiente a la banda edificable. La banda edificable es la franja que queda comprendida desde la  línea oficial hasta la línea de frente interno o línea interna de basamento según corresponda y determina el área donde puede edificarse dentro de un lote.","link":"https://data.buenosaires.gob.ar/dataset/superficie-edificable-en-planta","type":"vectortile","color":"#fbebb1","index":-1,"title":"Superficie edificable en planta (pisada)","options":{"type":"fill","paint":{"fill-color":"#fbebb1","fill-opacity":0.7,"fill-outline-color":"white"},"filter":["any",["==","tipo","basamento"],["==","tipo","cuerpo principal"]],"layout":{"visibility":"none"},"source":{"type":"vector","tiles":["https://vectortiles.usig.buenosaires.gob.ar/cur3d/volumen_edif/{z}/{x}/{y}.pbf?optimize=true"],"cluster":false,"maxzoom":18,"minzoom":10},"source-layer":"default"},"displayPopup":false,"popupContent":""},"timestamp_modificacion":"2022-09-19T13:05:46.431186"},{"id":18,"categoria":{"id":4,"nombre":"Bases de referencias","visibilidad":["cur3d"]},"nombre":"Catalogados","url":"https://vectortiles.usig.buenosaires.gob.ar/cur3d/aph_ssregic/","anio":2022,"tipo":"","origen_datos":"algoritmos_motor_reglas","autogenerado":null,"fuente":"PDI","frontend_config":{"id":"catalogados","info":"Parcelas consideradas áreas con valor patrimonial que poseen gran calidad urbana y arquitectónica. Para más información ver el Atlas de Edificios Catalogados.","link":"https://data.buenosaires.gob.ar/dataset/areas-proteccion-historica","type":"vectortile","color":"#19c3e3","title":"Catalogados","options":{"type":"fill","paint":{"fill-color":["match",["get","proteccion"],"CAUTELAR","#e9c46a","ESPECIAL","#f4a261","ESTRUCTURAL","#e76f51","INTEGRAL","#f94144","rgba(255,255,255,0)"],"fill-opacity":0.8},"layout":{"visibility":"none"},"source":{"type":"vector","tiles":["https://vectortiles.usig.buenosaires.gob.ar/cur3d/aph_ssregic/{z}/{x}/{y}.pbf?optimize=true"],"cluster":false,"maxzoom":18,"minzoom":10},"source-layer":"default"},"reference":[{"id":"cautelar","color":"#e9c46a","subTitle":"Cautelar"},{"id":"especial","color":"#f4a261","subTitle":"Especial"},{"id":"estructural","color":"#e76f51","subTitle":"Estructural"},{"id":"integral","color":"#f94144","subTitle":"Integral"}],"displayPopup":false,"popupContent":"{proteccion}"},"timestamp_modificacion":"2022-09-19T13:07:39.152567"},{"id":19,"categoria":{"id":4,"nombre":"Bases de referencias","visibilidad":["cur3d"]},"nombre":"Tejido 2D Alturas","url":"https://vectortiles.usig.buenosaires.gob.ar/cur3d/tejido/","anio":2022,"tipo":"","origen_datos":"algoritmos_motor_reglas","autogenerado":null,"fuente":"PDI","frontend_config":{"id":"tejido_2d_labels","info":"Plano correspondiente a la morfologia de la Ciudad elaborada mediante restitución Fotogramética. Esto puede abarcar tejido no registrado.","link":"https://data.buenosaires.gob.ar/dataset/tejido-urbano","type":"vectortile","color":"#212529","title":"Tejido 2D Alturas","options":{"type":"symbol","paint":{"text-color":"black","text-halo-color":"white","text-halo-width":1.5},"layout":{"text-font":["Open Sans Regular"],"text-size":10,"text-field":"{altura}","text-offset":[0.0,0.0]},"source":{"type":"vector","tiles":["https://vectortiles.usig.buenosaires.gob.ar/cur3d/tejido/{z}/{x}/{y}.pbf?optimize=true"],"cluster":false,"maxzoom":18,"minzoom":18},"source-layer":"default"},"displayPopup":false,"popupContent":""},"timestamp_modificacion":"2022-10-14T17:47:43.319964"},{"id":20,"categoria":{"id":4,"nombre":"Bases de referencias","visibilidad":["cur3d"]},"nombre":"Tejido 2D","url":"https://vectortiles.usig.buenosaires.gob.ar/cur3d/tejido/","anio":2022,"tipo":"","origen_datos":"algoritmos_motor_reglas","autogenerado":null,"fuente":"PDI","frontend_config":{"id":"tejido_2d","info":"Plano correspondiente a la morfologia de la Ciudad elaborada mediante restitución Fotogramética. Esto puede abarcar tejido no registrado.","link":"https://data.buenosaires.gob.ar/dataset/tejido-urbano","type":"vectortile","color":"#212529","title":"Tejido 2D","options":{"type":"fill","paint":{"fill-color":["case",["==",["get","altura"],0],"rgba(0,0,0,0)",["step",["get","altura"],"rgba(0,0,0,0)",1,"#e9ecef",6,"#dee2e6",9,"#ced4da",12,"#adb5bd",20,"#6c757d",30,"#495057",45,"#343a40",60,"#212529"]],"fill-opacity":1,"fill-outline-color":"white"},"layout":{"visibility":"none"},"source":{"type":"vector","tiles":["https://vectortiles.usig.buenosaires.gob.ar/cur3d/tejido/{z}/{x}/{y}.pbf?optimize=true"],"cluster":false,"maxzoom":18,"minzoom":10},"source-layer":"default"},"reference":[{"id":"6mts","color":"#e9ecef","subTitle":"1-6mts"},{"id":"9mts","color":"#dee2e6","subTitle":"6-9mts"},{"id":"12mts","color":"#ced4da","subTitle":"9-12mts"},{"id":"20mts","color":"#adb5bd","subTitle":"12-20mts"},{"id":"30mts","color":"#6c757d","subTitle":"20-30mts"},{"id":"45mts","color":"#495057","subTitle":"30-45mts"},{"id":"60mts","color":"#343a40","subTitle":"45-60mts"},{"id":"mas60mts","color":"#212529","subTitle":"60mts"}],"displayPopup":false,"popupContent":""},"timestamp_modificacion":"2025-07-01T11:42:33.388726"},{"id":21,"categoria":{"id":4,"nombre":"Bases de referencias","visibilidad":["cur3d"]},"nombre":"Tejido 3D","url":"https://vectortiles.usig.buenosaires.gob.ar/cur3d/tejido/","anio":2022,"tipo":"","origen_datos":"algoritmos_motor_reglas","autogenerado":null,"fuente":"PDI","frontend_config":{"id":"tejido","info":"Volumetría correspondiente a la edificación existente que  no alcanzó al menos el 75% de la altura máxima permitida para su unidad de edificabilidad.","link":"https://data.buenosaires.gob.ar/dataset/tejido-urbano","type":"vectortile","color":"white","index":5,"title":"Tejido 3D","options":{"type":"fill-extrusion","paint":{"fill-extrusion-color":"white","fill-extrusion-height":["get","altura"],"fill-extrusion-opacity":0.9},"filter":[">",["get","altura"],0],"layout":{"visibility":"none"},"source":{"type":"vector","tiles":["https://vectortiles.usig.buenosaires.gob.ar/cur3d/tejido/{z}/{x}/{y}.pbf?optimize=true"],"cluster":false,"maxzoom":18,"minzoom":10},"source-layer":"default"},"displayPopup":false,"popupContent":""},"timestamp_modificacion":"2025-08-11T11:09:06.734016"},{"id":22,"categoria":{"id":4,"nombre":"Bases de referencias","visibilidad":["cur3d"]},"nombre":"Manzanas atípicas","url":"https://vectortiles.usig.buenosaires.gob.ar/cur3d/manzana/","anio":2022,"tipo":"","origen_datos":"algoritmos_motor_reglas","autogenerado":null,"fuente":"PDI","frontend_config":{"id":"manz_atipica","info":"Superficie de terreno delimitada por vía pública y/o deslinde de corredor ferroviario y/o registrada como tal que cumple con alguna de las siguientes condiciones: tener 3, 5 o más de 5 lados, tener un lado curvo, tener una superficie inferior a cuatro mil metros cuadrados (4.000m2), o en caso de ser cuadrangular que la semisuma de dos de sus lados opuestos resulte inferior a sesenta y dos metros (62).","link":"https://data.buenosaires.gob.ar/dataset/manzanas","type":"vectortile","color":"#f562a2","title":"Manzanas atípicas","options":{"type":"fill","paint":{"fill-color":"#f562a2","fill-opacity":0.7},"filter":["==","tipo","ATIPICA"],"layout":{"visibility":"none"},"source":{"type":"vector","tiles":["https://vectortiles.usig.buenosaires.gob.ar/cur3d/manzana/{z}/{x}/{y}.pbf?optimize=true"],"cluster":false,"maxzoom":18,"minzoom":10},"source-layer":"default"},"displayPopup":false,"popupContent":""},"timestamp_modificacion":"2022-09-19T13:14:51.302555"},{"id":23,"categoria":{"id":4,"nombre":"Bases de referencias","visibilidad":["cur3d"]},"nombre":"Incidencia en UVA","url":"https://vectortiles.usig.buenosaires.gob.ar/cur3d/codigo_urbanistico/","anio":2022,"tipo":"","origen_datos":"algoritmos_motor_reglas","autogenerado":null,"fuente":"PDI","frontend_config":{"id":"codigourbanistico_uva","info":"Valor relativo del suelo según su localización, definido por manzana y medido en UVAs por metro cuadrado.","link":"https://data.buenosaires.gob.ar/dataset/codigo-urbanistico","type":"vectortile","color":"#fff5eb","title":"Incidencia en UVA","options":{"type":"fill","paint":{"fill-color":["match",["to-string",["get","alicuota"]],"0.1","#fff5eb","0.18","#fdbd83","0.27","#ee6510","0.35","#7f2704","#fff"],"fill-opacity":0.8},"layout":{"visibility":"none"},"source":{"type":"vector","tiles":["https://vectortiles.usig.buenosaires.gob.ar/cur3d/codigo_urbanistico/{z}/{x}/{y}.pbf?optimize=true"],"cluster":false,"maxzoom":18,"minzoom":10},"source-layer":"default"},"reference":[{"id":"zone1","color":"#fff5eb","subTitle":"Zona 1"},{"id":"zone2","color":"#fdbd83","subTitle":"Zona 2"},{"id":"zone3","color":"#ee6510","subTitle":"Zona 3"},{"id":"zone4","color":"#7f2704","subTitle":"Zona 4"}],"displayPopup":false,"popupContent":""},"timestamp_modificacion":"2022-09-19T13:16:22.490033"},{"id":24,"categoria":{"id":4,"nombre":"Bases de referencias","visibilidad":["cur3d"]},"nombre":"Mixtura de usos de suelo","url":"https://vectortiles.usig.buenosaires.gob.ar/cur3d/codigo_urbanistico/","anio":2022,"tipo":"","origen_datos":"algoritmos_motor_reglas","autogenerado":null,"fuente":"PDI","frontend_config":{"id":"codigourbanistico_mixtura","info":"Consiste en la posibilidad de aplicación de usos diversos pero compatibles dentro de una misma área.","link":"https://data.buenosaires.gob.ar/dataset/codigo-urbanistico","type":"vectortile","color":"#e76056","title":"Mixtura de usos de suelo","options":{"type":"fill","paint":{"fill-color":["match",["get","uso_1"],1,"#3b0f6f",2,"#8c2981",3,"#de4969",4,"#fe9f6d","#fff"],"fill-opacity":0.8},"layout":{"visibility":"none"},"source":{"type":"vector","tiles":["https://vectortiles.usig.buenosaires.gob.ar/cur3d/codigo_urbanistico/{z}/{x}/{y}.pbf?optimize=true"],"cluster":false,"maxzoom":18,"minzoom":10},"source-layer":"default"},"reference":[{"id":"use1","color":"#3b0f6f","subTitle":"Uso 1"},{"id":"use2","color":"#8c2981","subTitle":"Uso 2"},{"id":"use3","color":"#de4969","subTitle":"Uso 3"},{"id":"use4","color":"#fe9f6d","subTitle":"Uso 4"}],"displayPopup":false,"popupContent":"{uso_1}"},"timestamp_modificacion":"2022-09-19T13:17:55.918698"},{"id":25,"categoria":{"id":5,"nombre":"Lotes con afectaciones","visibilidad":["cur3d"]},"nombre":"Riesgo Hídrico","url":"https://vectortiles.usig.buenosaires.gob.ar/cur3d/cur_riesgo_hidrico/","anio":2022,"tipo":"","origen_datos":"algoritmos_motor_reglas","autogenerado":null,"fuente":"PDI","frontend_config":{"id":"riesgo_hidrico","info":"Corresponde a zonas con vulnerabilidad a las inundaciones.","link":"https://data.buenosaires.gob.ar/dataset/riesgo-hidrico","type":"vectortile","color":"#224778","title":"Riesgo Hídrico","options":{"type":"fill","paint":{"fill-color":"#224778","fill-opacity":0.4},"layout":{"visibility":"none"},"source":{"type":"vector","tiles":["https://vectortiles.usig.buenosaires.gob.ar/cur3d/cur_riesgo_hidrico/{z}/{x}/{y}.pbf?optimize=true"],"cluster":false,"maxzoom":18,"minzoom":10},"source-layer":"default"},"displayPopup":false,"popupContent":""},"timestamp_modificacion":"2025-09-03T14:09:57.591631"},{"id":26,"categoria":{"id":5,"nombre":"Lotes con afectaciones","visibilidad":["cur3d"]},"nombre":"Cono Aproximación Aeroparque","url":"https://vectortiles.usig.buenosaires.gob.ar/cur3d/restricciones/","anio":2022,"tipo":"","origen_datos":"algoritmos_motor_reglas","autogenerado":null,"fuente":"PDI","frontend_config":{"id":"restricciones_aeroparque","info":"Limitación de altura en función de la regulación aeronáutica.","link":"https://data.buenosaires.gob.ar/dataset/lineas-constructivas-particularizadas","type":"vectortile","color":"goldenrod","title":"Cono Aproximación Aeroparque","options":{"type":"line","paint":{"line-color":"goldenrod","line-width":4},"filter":["==","tipo","Limitación de Altura Aeronáutica"],"layout":{"visibility":"none"},"source":{"type":"vector","tiles":["https://vectortiles.usig.buenosaires.gob.ar/cur3d/restricciones/{z}/{x}/{y}.pbf?optimize=true"],"cluster":false,"maxzoom":18,"minzoom":10},"source-layer":"default"},"displayPopup":false,"popupContent":""},"timestamp_modificacion":"2025-11-05T11:35:54.075032"},{"id":27,"categoria":{"id":5,"nombre":"Lotes con afectaciones","visibilidad":["cur3d"]},"nombre":"Polígono Área de Desarrollo Prioritario Sur (ADPS)","url":"https://epok.buenosaires.gob.ar/getGeoLayer/?categoria=adps_poligono&formato=geojson&srid=4326","anio":2023,"tipo":"POLYGON","origen_datos":"algoritmos_motor_reglas","autogenerado":null,"fuente":"PDI","frontend_config":{"id":"ADPS","info":"","link":null,"type":"custom","color":"#640b0d","title":"Polígono Área de Desarrollo Prioritario Sur (ADPS)","options":[{"id":"ADPS","type":"fill","paint":{"fill-color":["match",["get","Id"],"adps_poligono|1","#640b0d","#fbac23"],"fill-opacity":0.4},"source":{"id":"source_ADPS","data":"https://epok.buenosaires.gob.ar/getGeoLayer/?categoria=adps_poligono&formato=geojson&srid=4326","type":"geojson","cluster":false}}],"displayPopup":false,"popupContent":"{tipo}"},"timestamp_modificacion":"2024-01-05T15:22:41.975804"},{"id":28,"categoria":{"id":5,"nombre":"Lotes con afectaciones","visibilidad":["cur3d"]},"nombre":"Polígono Área de Microcentro","url":"https://epok.buenosaires.gob.ar/getGeoLayer/?categoria=microcentro&formato=geojson&srid=4326","anio":2023,"tipo":"POLYGON","origen_datos":"algoritmos_motor_reglas","autogenerado":null,"fuente":"PDI","frontend_config":{"id":"poligono_area_de_microcentro","info":"","link":null,"type":"custom","color":"#e41a1c","title":"Polígono Área de Microcentro","options":[{"id":"poligono_area_de_microcentro","type":"fill","paint":{"fill-color":["match",["get","Id"],"microcentro|1","#e41a1c","#fbac23"],"fill-opacity":0.4},"source":{"id":"source_poligono_area_de_microcentro","data":"https://epok.buenosaires.gob.ar/getGeoLayer/?categoria=microcentro&formato=geojson&srid=4326","type":"geojson","cluster":false}}],"displayPopup":false,"popupContent":"{tipo}"},"timestamp_modificacion":"2024-01-05T15:24:44.578652"},{"id":29,"categoria":{"id":5,"nombre":"Lotes con afectaciones","visibilidad":["cur3d"]},"nombre":"Línea de Edificación Particularizada","url":"https://vectortiles.usig.buenosaires.gob.ar/cur3d/restricciones/","anio":2022,"tipo":"","origen_datos":"algoritmos_motor_reglas","autogenerado":null,"fuente":"PDI","frontend_config":{"id":"restricciones_particularizada","info":"Es la línea de edificación a usar por una nueva edificación.","link":"https://data.buenosaires.gob.ar/dataset/lineas-constructivas-particularizadas","type":"vectortile","color":"#2ebc98","title":"Línea de Edificación Particularizada","options":{"type":"line","paint":{"line-color":"#2ebc98","line-width":4},"filter":["==","tipo","Línea Particularizada"],"layout":{"visibility":"none"},"source":{"type":"vector","tiles":["https://vectortiles.usig.buenosaires.gob.ar/cur3d/restricciones/{z}/{x}/{y}.pbf?optimize=true"],"cluster":false,"maxzoom":18,"minzoom":10},"source-layer":"default"},"displayPopup":false,"popupContent":"{tipo}"},"timestamp_modificacion":"2025-11-05T11:36:13.541211"},{"id":30,"categoria":{"id":5,"nombre":"Lotes con afectaciones","visibilidad":["cur3d"]},"nombre":"Ensanche","url":"https://vectortiles.usig.buenosaires.gob.ar/cur3d/restricciones/","anio":2022,"tipo":"","origen_datos":"algoritmos_motor_reglas","autogenerado":null,"fuente":"PDI","frontend_config":{"id":"restricciones_ensanche","info":"Ampliación o prolongación de una vía.","link":"https://data.buenosaires.gob.ar/dataset/lineas-constructivas-particularizadas","type":"vectortile","color":"#99c25f","title":"Ensanche","options":{"type":"line","paint":{"line-color":"#99c25f","line-width":4},"filter":["==","tipo","Línea de Afectación"],"layout":{"visibility":"none"},"source":{"type":"vector","tiles":["https://vectortiles.usig.buenosaires.gob.ar/cur3d/restricciones/{z}/{x}/{y}.pbf?optimize=true"],"cluster":false,"maxzoom":18,"minzoom":10},"source-layer":"default"},"displayPopup":false,"popupContent":"{tipo}"},"timestamp_modificacion":"2025-11-05T11:36:29.938717"},{"id":31,"categoria":{"id":5,"nombre":"Lotes con afectaciones","visibilidad":["cur3d"]},"nombre":"Apertura","url":"https://vectortiles.usig.buenosaires.gob.ar/cur3d/restricciones/","anio":2022,"tipo":"","origen_datos":"algoritmos_motor_reglas","autogenerado":null,"fuente":"PDI","frontend_config":{"id":"restricciones_apretura","info":"Apertura de una vía.","link":"https://data.buenosaires.gob.ar/dataset/lineas-constructivas-particularizadas","type":"vectortile","color":"#19c3e3","title":"Apertura","options":{"type":"line","paint":{"line-color":"#19c3e3","line-width":4},"filter":["==","tipo","Apertura de calle"],"layout":{"visibility":"none"},"source":{"type":"vector","tiles":["https://vectortiles.usig.buenosaires.gob.ar/cur3d/restricciones/{z}/{x}/{y}.pbf?optimize=true"],"cluster":false,"maxzoom":18,"minzoom":10},"source-layer":"default"},"displayPopup":false,"popupContent":""},"timestamp_modificacion":"2025-11-05T11:36:47.159199"},{"id":32,"categoria":{"id":6,"nombre":"Entorno","visibilidad":["cur3d"]},"nombre":"Establecimientos educativos","url":"https://epok.buenosaires.gob.ar/getGeoLayer/?categoria=establecimientos_educativos_de_gestion_privada&formato=geojson&srid=4326","anio":2022,"tipo":"","origen_datos":"epok_pgd","autogenerado":null,"fuente":"","frontend_config":{"id":"establecimientos_educativos_de_gestion_privada","icon":"https://epok.buenosaires.gob.ar//media/repok/uploads/mapainteractivoba/mapabsas_espacios_de_formacion.png","info":null,"link":null,"type":"custom","color":"#15D1C9","title":"Establecimientos educativos","images":[{"id":"establecimiento_educativo_de_gestion_privada","data":"https://epok.buenosaires.gob.ar/media/repok/uploads/mapainteractivoba/3_establecimiento_educativo_b.png"},{"id":"establecimiento_educativo_de_gestion_estatal","data":"https://epok.buenosaires.gob.ar/media/repok/uploads/mapainteractivoba/establecimientos_educativos_publicos.png"}],"options":[{"id":"establecimientos_educativos_de_gestion_privada_clustered_big_circle","type":"circle","paint":{"circle-color":"rgba(110,204,57,.6)","circle-radius":15},"filter":["has","point_count"],"source":{"id":"source_establecimientos_educativos_de_gestion_privada","data":"https://epok.buenosaires.gob.ar/getGeoLayer/?categoria=establecimientos_educativos_de_gestion_privada&formato=geojson&srid=4326","type":"geojson","cluster":true,"clusterRadius":35,"clusterMaxZoom":14}},{"id":"establecimientos_educativos_de_gestion_privada_clustered_small_circle","type":"circle","paint":{"circle-color":"rgba(110,204,57,.6)","circle-radius":11},"filter":["has","point_count"],"source":{"id":"source_establecimientos_educativos_de_gestion_privada","data":"https://epok.buenosaires.gob.ar/getGeoLayer/?categoria=establecimientos_educativos_de_gestion_privada&formato=geojson&srid=4326","type":"geojson","cluster":true,"clusterRadius":35,"clusterMaxZoom":14}},{"id":"establecimientos_educativos_de_gestion_privada","type":"symbol","paint":{"text-color":"#333333"},"layout":{"icon-size":1,"text-font":["Klokantech Noto Sans Bold"],"text-size":12,"icon-image":["case",["has","point_count"],"","establecimiento_educativo_de_gestion_privada"],"text-field":["case",["has","point_count"],["get","point_count_abbreviated"],""],"icon-allow-overlap":true},"source":{"id":"source_establecimientos_educativos_de_gestion_privada","data":"https://epok.buenosaires.gob.ar/getGeoLayer/?categoria=establecimientos_educativos_de_gestion_privada&formato=geojson&srid=4326","type":"geojson","cluster":true,"clusterRadius":35,"clusterMaxZoom":14}},{"id":"establecimientos_educativos_de_gestion_estatal_clustered_big_circle","type":"circle","paint":{"circle-color":"rgba(0,111,255,.6)","circle-radius":15},"filter":["has","point_count"],"source":{"id":"source_establecimientos_educativos_de_gestion_estatal","data":"https://epok.buenosaires.gob.ar/getGeoLayer/?categoria=establecimientos_educativos_de_gestion_estatal&formato=geojson&srid=4326","type":"geojson","cluster":true,"clusterRadius":35,"clusterMaxZoom":14}},{"id":"establecimientos_educativos_de_gestion_estatal_clustered_small_circle","type":"circle","paint":{"circle-color":"rgba(0,111,255,.6)","circle-radius":11},"filter":["has","point_count"],"source":{"id":"source_establecimientos_educativos_de_gestion_estatal","data":"https://epok.buenosaires.gob.ar/getGeoLayer/?categoria=establecimientos_educativos_de_gestion_estatal&formato=geojson&srid=4326","type":"geojson","cluster":true,"clusterRadius":35,"clusterMaxZoom":14}},{"id":"establecimientos_educativos_de_gestion_estatal","type":"symbol","paint":{"text-color":"#333333"},"layout":{"icon-size":1,"text-font":["Klokantech Noto Sans Bold"],"text-size":12,"icon-image":["case",["has","point_count"],"","establecimiento_educativo_de_gestion_estatal"],"text-field":["case",["has","point_count"],["get","point_count_abbreviated"],""],"icon-allow-overlap":true},"source":{"id":"source_establecimientos_educativos_de_gestion_estatal","data":"https://epok.buenosaires.gob.ar/getGeoLayer/?categoria=establecimientos_educativos_de_gestion_estatal&formato=geojson&srid=4326","type":"geojson","cluster":true,"clusterRadius":35,"clusterMaxZoom":14}}],"reference":[{"id":"publica","color":"#1542E2","subTitle":"Pública"},{"id":"privada","color":"#009863","subTitle":"Privada"}],"displayPopup":true,"popupContent":"[\"nombre\", \"direccion\", \"niveles_y_modalidades\"]"},"timestamp_modificacion":"2022-10-19T09:44:17.792126"},{"id":33,"categoria":{"id":6,"nombre":"Entorno","visibilidad":["cur3d"]},"nombre":"Establecimientos de salud","url":"https://epok.buenosaires.gob.ar","anio":2022,"tipo":"","origen_datos":"epok_pgd","autogenerado":null,"fuente":"","frontend_config":{"id":"hospitales_de_ninos","icon":"https://epok.buenosaires.gob.ar/media/repok/uploads/mapainteractivoba/mapabsas_salud.png","info":null,"link":null,"type":"custom","color":"#cd0000","title":"Establecimientos de salud","images":[{"id":"hospitales","data":"https://epok.buenosaires.gob.ar/media/repok/uploads/mapainteractivoba/hospitales.png"},{"id":"cesac","data":"https://epok.buenosaires.gob.ar/media/repok/uploads/mapainteractivoba/cesac.png"}],"options":[{"id":"hospitales_de_ninos","type":"symbol","layout":{"icon-size":["interpolate",["linear"],["zoom"],10,0.5,15,1],"icon-image":"hospitales","icon-allow-overlap":true},"source":{"id":"source_hospitales_de_ninos","data":"https://epok.buenosaires.gob.ar/getGeoLayer/?categoria=hospitales_de_ninos&formato=geojson&srid=4326","type":"geojson"}},{"id":"hospitales_especializados","type":"symbol","layout":{"icon-size":["interpolate",["linear"],["zoom"],10,0.5,15,1],"icon-image":"hospitales","icon-allow-overlap":true},"source":{"id":"source_hospitales_especializados","data":"https://epok.buenosaires.gob.ar/getGeoLayer/?categoria=hospitales_especializados&formato=geojson&srid=4326","type":"geojson"}},{"id":"hospitales_generales_de_agudos","type":"symbol","layout":{"icon-size":["interpolate",["linear"],["zoom"],10,0.5,15,1],"icon-image":"hospitales","icon-allow-overlap":true},"source":{"id":"source_hospitales_generales_de_agudos","data":"https://epok.buenosaires.gob.ar/getGeoLayer/?categoria=hospitales_generales_de_agudos&formato=geojson&srid=4326","type":"geojson"}},{"id":"centros_de_salud_y_accion_comunitaria","type":"symbol","layout":{"icon-size":["interpolate",["linear"],["zoom"],10,0.5,15,1],"icon-image":"cesac","icon-allow-overlap":true},"source":{"id":"source_centros_de_salud_y_accion_comunitaria","data":"https://epok.buenosaires.gob.ar/getGeoLayer/?categoria=centros_de_salud_y_accion_comunitaria&formato=geojson&srid=4326","type":"geojson"}}],"reference":[{"id":"hospital","color":"#cd0000","subTitle":"Hospital"},{"id":"cesac","color":"#44d3fa","subTitle":"Centro de salud"}],"displayPopup":true,"popupContent":"[\"nombre\", \"direccion\", \"especialidad\"]"},"timestamp_modificacion":"2022-10-19T09:49:13.243810"},{"id":34,"categoria":{"id":6,"nombre":"Entorno","visibilidad":["cur3d"]},"nombre":"Edificios públicos","url":"https://epok.buenosaires.gob.ar/pub/mapa/culturaserviciopublico/edificios_publicos","anio":2019,"tipo":"","origen_datos":"epok_pgd","autogenerado":null,"fuente":"","frontend_config":{"id":"edificios_publicos","icon":"https://static.usig.buenosaires.gob.ar/symbols//edificios_publicos.png","info":null,"link":null,"type":"custom","color":"#ffcd00","title":"Edificios públicos","images":[{"id":"edificios_publicos","data":"https://static.usig.buenosaires.gob.ar/symbols//edificios_publicos.png"}],"options":[{"id":"edificios_publicos","type":"symbol","layout":{"icon-size":["interpolate",["linear"],["zoom"],10,0.5,15,1],"icon-image":"edificios_publicos","icon-allow-overlap":true},"source":{"id":"source_edificios_publicos","data":"https://epok.buenosaires.gob.ar/getGeoLayer/?categoria=edificios_publicos_gcba_custom&formato=geojson&srid=4326","type":"geojson","cluster":false,"clusterRadius":35,"clusterMaxZoom":14}}],"displayPopup":true,"popupContent":"[\"nombre\", \"direccion\", \"repartición/ministerio\"]"},"timestamp_modificacion":"2022-10-20T09:50:18.415701"},{"id":35,"categoria":{"id":7,"nombre":"Movilidad","visibilidad":["cur3d"]},"nombre":"Estaciones de ecobici","url":"https://epok.buenosaires.gob.ar/getGeoLayer/?categoria=estaciones_de_bicicletas&formato=geojson&srid=4326","anio":null,"tipo":"","origen_datos":"epok_pgd","autogenerado":null,"fuente":"","frontend_config":{"id":"estaciones_de_bicicletas","icon":"https://epok.buenosaires.gob.ar//media/repok/uploads/mapainteractivoba/estacion_ecobici.png","info":null,"link":null,"type":"custom","color":"#15D1C9","title":"Estaciones de ecobici","images":[{"id":"estacion_ecobici","data":"https://epok.buenosaires.gob.ar/media/repok/uploads/mapainteractivoba/estacion_ecobici.png"}],"options":[{"id":"ciclovias","type":"raster","paint":{},"source":{"id":"source_ciclovias","type":"raster","tiles":["https://servicios.usig.buenosaires.gob.ar/mapcache/tms/1.0.0/ciclovias_caba_3857@GoogleMapsCompatible/{z}/{x}/{y}.png"],"scheme":"tms","tileSize":256}},{"id":"estaciones_de_bicicletas_clustered_big_circle","type":"circle","paint":{"circle-color":"rgba(110,204,57,.6)","circle-radius":15},"filter":["has","point_count"],"source":{"id":"source_estaciones_de_bicicletas","data":"https://epok.buenosaires.gob.ar/getGeoLayer/?categoria=estaciones_de_bicicletas&formato=geojson&srid=4326","type":"geojson","cluster":true,"clusterRadius":35,"clusterMaxZoom":14}},{"id":"estaciones_de_bicicletas_clustered_small_circle","type":"circle","paint":{"circle-color":"rgba(110,204,57,.6)","circle-radius":11},"filter":["has","point_count"],"source":{"id":"source_estaciones_de_bicicletasa","data":"https://epok.buenosaires.gob.ar/getGeoLayer/?categoria=estaciones_de_bicicletas&formato=geojson&srid=4326","type":"geojson","cluster":true,"clusterRadius":35,"clusterMaxZoom":14}},{"id":"estaciones_de_bicicletas","type":"symbol","paint":{"text-color":"#333333"},"layout":{"icon-size":1,"text-font":["Klokantech Noto Sans Bold"],"text-size":12,"icon-image":["case",["has","point_count"],"","estacion_ecobici"],"text-field":["case",["has","point_count"],["get","point_count_abbreviated"],""],"icon-allow-overlap":true},"source":{"id":"source_estaciones_de_bicicletas","data":"https://epok.buenosaires.gob.ar/getGeoLayer/?categoria=estaciones_de_bicicletas&formato=geojson&srid=4326","type":"geojson","cluster":true,"clusterRadius":35,"clusterMaxZoom":14}}],"displayPopup":true,"popupContent":"[\"nombre\", \"direccion\", \"niveles_y_modalidades\"]"},"timestamp_modificacion":"2022-10-21T07:45:13.934350"},{"id":36,"categoria":{"id":7,"nombre":"Movilidad","visibilidad":["cur3d"]},"nombre":"subtes","url":"https://epok.buenosaires.gob.ar/getGeoLayer/?categoria=lineas_de_subte&formato=geojson&srid=4326","anio":2019,"tipo":"LINESTRING","origen_datos":"epok_pgd","autogenerado":null,"fuente":"","frontend_config":{"id":"estaciones_sbase","icon":"https://epok.buenosaires.gob.ar/media/repok/uploads/mapainteractivoba/estacion_de_subte_cd3d.png","info":null,"link":null,"type":"custom","color":"#ffcd00","title":"Subtes","images":[{"id":"subte_linea_a","data":"https://epok.buenosaires.gob.ar//media/repok/uploads/mapainteractivoba/subte_linea_a.png"},{"id":"subte_linea_b","data":"https://epok.buenosaires.gob.ar//media/repok/uploads/mapainteractivoba/subte_linea_b.png"},{"id":"subte_linea_c","data":"https://epok.buenosaires.gob.ar//media/repok/uploads/mapainteractivoba/subte_linea_c.png"},{"id":"subte_linea_d","data":"https://epok.buenosaires.gob.ar//media/repok/uploads/mapainteractivoba/subte_linea_d.png"},{"id":"subte_linea_e","data":"https://epok.buenosaires.gob.ar//media/repok/uploads/mapainteractivoba/subte_linea_e.png"},{"id":"subte_linea_h","data":"https://epok.buenosaires.gob.ar//media/repok/uploads/mapainteractivoba/subte_linea_h.png"}],"options":[{"id":"lineas_de_subte","type":"line","paint":{"line-color":["match",["get","Linea"],"A","rgb(28, 164, 203)","B","rgb(194, 9, 36)","C","rgb(0, 62, 161)","D","rgb(33, 120, 97)","E","rgb(107, 41, 126)","H","rgb(244, 204, 33)","#fbac23"],"line-width":["interpolate",["linear"],["zoom"],10,1,15,8]},"layout":{"line-cap":"round","line-join":"round"},"source":{"id":"source_lineas_de_subte","data":"https://epok.buenosaires.gob.ar/getGeoLayer/?categoria=lineas_de_subte&formato=geojson&srid=4326","type":"geojson","cluster":false,"clusterRadius":35,"clusterMaxZoom":14}},{"id":"estaciones_sbase","type":"symbol","layout":{"icon-size":["interpolate",["linear"],["zoom"],10,0.5,15,1],"icon-image":["match",["get","Linea"],"A","subte_linea_a","B","subte_linea_b","C","subte_linea_c","D","subte_linea_d","E","subte_linea_e","H","subte_linea_h","subte_linea_a"],"icon-allow-overlap":true},"source":{"id":"source_estaciones_sbase","data":"https://epok.buenosaires.gob.ar/getGeoLayer/?categoria=estaciones_sbase&formato=geojson&srid=4326","type":"geojson","cluster":false}}],"reference":[{"id":"a","icon":"https://epok.buenosaires.gob.ar//media/repok/uploads/mapainteractivoba/subte_linea_a.png","color":"rgb(28, 164, 203)","subTitle":"Linea A"},{"id":"b","icon":"https://epok.buenosaires.gob.ar//media/repok/uploads/mapainteractivoba/subte_linea_b.png","color":"rgb(194, 9, 36)","subTitle":"Linea B"},{"id":"c","icon":"https://epok.buenosaires.gob.ar//media/repok/uploads/mapainteractivoba/subte_linea_c.png","color":"rgb(0, 62, 161)","subTitle":"Linea C"},{"id":"d","icon":"https://epok.buenosaires.gob.ar//media/repok/uploads/mapainteractivoba/subte_linea_d.png","color":"rgb(33, 120, 97)","subTitle":"Linea D"},{"id":"e","icon":"https://epok.buenosaires.gob.ar//media/repok/uploads/mapainteractivoba/subte_linea_e.png","color":"rgb(107, 41, 126)","subTitle":"Linea E"},{"id":"h","icon":"https://epok.buenosaires.gob.ar//media/repok/uploads/mapainteractivoba/subte_linea_h.png","color":"rgb(244, 204, 33)","subTitle":"Linea H"}],"displayPopup":true,"popupContent":"[\"nombre\", \"_linea\"]"},"timestamp_modificacion":"2022-11-12T12:55:04.334228"},{"id":37,"categoria":{"id":7,"nombre":"Movilidad","visibilidad":["cur3d"]},"nombre":"distritos","url":"https://epok.buenosaires.gob.ar/getGeoLayer/?categoria=distritos&formato=geojson&srid=4326","anio":null,"tipo":"MULTIPOLYGON","origen_datos":"epok_pgd","autogenerado":null,"fuente":"","frontend_config":{"id":"distritos","info":null,"link":null,"type":"custom","color":"#808080","title":"Distritos","images":[],"options":[{"id":"distritos","type":"fill","paint":{"fill-color":["match",["get","Id"],"distritos|1","rgba(255, 0, 140, 0.5)","distritos|2","rgba(208, 24, 27, 0.5)","distritos|3","rgba(213, 101, 254, 0.5)","distritos|4","rgba(120, 165, 253, 0.5)","distritos|5","rgba(33, 163, 89, 0.5)","distritos|6","rgba(136, 0, 21, 0.5)","#fbac23"],"fill-outline-color":["match",["get","Id"],"distritos|1","rgb(255, 0, 140)","distritos|2","rgb(208, 24, 27)","distritos|3","rgb(213, 101, 254)","distritos|4","rgb(120, 165, 253)","distritos|5","rgb(33, 163, 89)","distritos|6","rgb(136, 0, 21)","#fbac23"]},"source":{"id":"source_distritos","data":"https://epok.buenosaires.gob.ar/getGeoLayer/?categoria=distritos&formato=geojson&srid=4326","type":"geojson","cluster":false}},{"id":"distritos_bordes","type":"line","paint":{"line-color":["match",["get","Id"],"distritos|1","rgb(255, 0, 140)","distritos|2","rgb(208, 24, 27)","distritos|3","rgb(213, 101, 254)","distritos|4","rgb(120, 165, 253)","distritos|5","rgb(33, 163, 89)","distritos|6","rgb(136, 0, 21)","#fbac23"],"line-width":4},"source":{"id":"source_distritos","data":"https://epok.buenosaires.gob.ar/getGeoLayer/?categoria=distritos&formato=geojson&srid=4326","type":"geojson","cluster":false}}],"reference":[{"id":"1","color":"rgb(255, 0, 140)","subTitle":"Distrito del diseño"},{"id":"2","color":"rgb(208, 24, 27)","subTitle":"Distrito de las artes"},{"id":"3","color":"rgb(213, 101, 254)","subTitle":"Distrito audiovisual"},{"id":"4","color":"rgb(120, 165, 253)","subTitle":"Distrito tecnológico"},{"id":"5","color":"rgb(33, 163, 89)","subTitle":"Distrito del deporte"},{"id":"6","color":"rgb(136, 0, 21)","subTitle":"Distrito del vino"}],"displayPopup":true,"popupContent":"[\"nombre\", \"direccion\", \"barrio\", \"comuna\"]"},"timestamp_modificacion":"2022-11-11T08:02:41.215728"},{"id":38,"categoria":{"id":8,"nombre":"Ambiente/Sustentabilidad","visibilidad":["cur3d"]},"nombre":"Mapa de Radiación Solar","url":"https://epok.buenosaires.gob.ar","anio":null,"tipo":"VARIOS","origen_datos":"epok_pgd","autogenerado":null,"fuente":"","frontend_config":{"id":"mapa_de_radiacion","info":"","link":"https://data.buenosaires.gob.ar/dataset/mapa-solar","type":"vectortile","color":"rgb(243,114,32)","title":"Mapa de Radiación Solar","options":[{"id":"mapa_de_radiacion","type":"raster","paint":{"raster-opacity":0.7},"source":{"id":"source_mapa_de_radiacion","type":"raster","tiles":["https://servicios.usig.buenosaires.gob.ar/mapcache/tms/1.0.0/mapasolar_3857@GoogleMapsCompatible/{z}/{x}/{y}.png"],"scheme":"tms","tileSize":256}}],"reference":[{"id":"0_276.915","color":"rgb(43,131,186)","subTitle":"0 - 276.915 Wh/m2"},{"id":"276.915_551.603","color":"rgb(116,183,174)","subTitle":"276.915 - 551.603 Wh/m2"},{"id":"551.603_756.308","color":"rgb(183,226,168)","subTitle":"551.603 - 756.308 Wh/m2"},{"id":"756.308_921.487","color":"rgb(231,246,184)","subTitle":"756.308 - 921.487 Wh/m2"},{"id":"921.487_1058.661","color":"rgb( 255, 232, 164 )","subTitle":"921.487 - 1058.661 Wh/m2"},{"id":"1058.661_1180.230","color":"rgb( 254, 186, 110 )","subTitle":"1058.661 - 1180.230 Wh/m2"},{"id":"1180.230_1297.001","color":"rgb( 237, 110, 67 )","subTitle":"1180.230 - 1297.001 Wh/m2"},{"id":"1297.001_1502.890","color":"rgb(237,110,67)","subTitle":"1297.001 - 1502.890 Wh/m2"}],"displayPopup":false,"popupContent":"{tipo}"},"timestamp_modificacion":"2023-05-05T14:30:29.109926"},{"id":39,"categoria":{"id":5,"nombre":"Lotes con afectaciones","visibilidad":["cur3d"]},"nombre":"Cinturón Digital","url":"https://vectortiles.usig.buenosaires.gob.ar/cur3d/restricciones/","anio":2022,"tipo":"","origen_datos":"algoritmos_motor_reglas","autogenerado":null,"fuente":"PDI","frontend_config":{"id":"restricciones_cinturon","info":"Área en la que se restringe la altura por estar afectada a corredores radioeléctricos.","link":"https://data.buenosaires.gob.ar/dataset/lineas-constructivas-particularizadas","type":"vectortile","color":"#0389d1","title":"Cinturón Digital","options":{"type":"line","paint":{"line-color":"#0389d1","line-width":4},"filter":["==","tipo","Cinturón Digital"],"layout":{"visibility":"none"},"source":{"type":"vector","tiles":["https://vectortiles.usig.buenosaires.gob.ar/cur3d/restricciones/{z}/{x}/{y}.pbf?optimize=true"],"cluster":false,"maxzoom":18,"minzoom":10},"source-layer":"default"},"displayPopup":false,"popupContent":""},"timestamp_modificacion":"2025-11-05T11:37:31.699689"},{"id":40,"categoria":{"id":5,"nombre":"Lotes con afectaciones","visibilidad":["cur3d"]},"nombre":"Riesgo Arqueológico","url":"https://vectortiles.usig.buenosaires.gob.ar/cur3d/cur_riesgo_arqueologico/","anio":2022,"tipo":"VARIOS","origen_datos":"algoritmos_motor_reglas","autogenerado":null,"fuente":"PDI","frontend_config":{"id":"riesgo_arqueologico","info":"A revisar.","link":"https://data.buenosaires.gob.ar/dataset/riesgo-arqueologico","type":"vectortile","color":"#19c3e3","title":"Riesgo Arqueológico","options":{"type":"fill","paint":{"fill-color":["match",["get","tipo"],"Radio Antiguo","#a851b2","Casco Pueblo de Flores","#fead3a","Casco Pueblo de Belgrano","#fd8793","Villa Riachuelo","#000000","Frente Costero de la Ciudad","#1e7db3","Palermo","#286152","La Quema","#707521","Parque Avellaneda","#4c907b","Chacra de Castro","#fd5c02","rgba(255,255,255,0)"],"fill-opacity":0.4},"layout":{"visibility":"none"},"source":{"type":"vector","tiles":["https://vectortiles.usig.buenosaires.gob.ar/cur3d/cur_riesgo_arqueologico/{z}/{x}/{y}.pbf?optimize=true"],"cluster":false,"maxzoom":18,"minzoom":10},"source-layer":"default"},"reference":[{"id":"radio_antiguo","color":"#a851b2","subTitle":"Radio Antiguo"},{"id":"casco_pueblo_de_flores","color":"#fead3a","subTitle":"Casco Pueblo de Flores"},{"id":"casco_pueblo_de_belgrano","color":"#fd8793","subTitle":"Casco Pueblo de Belgrano"},{"id":"villa_riachuelo","color":"#000000","subTitle":"Villa Riachuelo"},{"id":"frente_costero_de_la_ciudad","color":"#1e7db3","subTitle":"Frente Costero de la Ciudad"},{"id":"palermo","color":"#286152","subTitle":"Palermo"},{"id":"la_quema","color":"#707521","subTitle":"La Quema"},{"id":"parque_avellaneda","color":"#4c907b","subTitle":"Parque Avellaneda"},{"id":"chacra_de_castro","color":"#fd5c02","subTitle":"Chacra de Castro"}],"displayPopup":false,"popupContent":"{tipo}"},"timestamp_modificacion":"2024-01-05T15:32:13.395343"},{"id":41,"categoria":{"id":4,"nombre":"Bases de referencias","visibilidad":["cur3d"]},"nombre":"Planchetas_Cur","url":"https://vectortiles.usig.buenosaires.gob.ar/cur3d/restricciones/","anio":2024,"tipo":"MULTIPOLYGON","origen_datos":"algoritmos_motor_reglas","autogenerado":"2024-04-11T12:51:23","fuente":"PDI","frontend_config":{"id":"Plancheta_CUr","info":"Planchetas","link":"https://data.buenosaires.gob.ar/dataset/codigo-urbanistico","type":"vectortile","color":"rgb(162, 59, 38)","title":"Plancheta CUr","options":{"type":"line","paint":{"line-color":"#000000"},"layout":{},"source":{"data":"https://epok-qa.gcba.gob.ar/getGeoLayer/?categoria=cur3d_grillaplanchetas&formato=geojson&formato=geojson&srid=4326","type":"geojson","cluster":false}},"displayPopup":false,"popupContent":""},"timestamp_modificacion":"2024-04-11T12:52:46.458698"}]},"mapa_interactivo":{"cantidad":8,"mbtiles":[{"id":1,"categoria":{"id":1,"nombre":"Fotografías aéreas","visibilidad":["cur3d","mapa_interactivo"]},"nombre":"Foto aérea CABA 1940","url":"https://vectortiles.usig.buenosaires.gob.ar/aereas/fotografias_aereas_1940_caba_3857/","anio":1940,"tipo":"aerea","origen_datos":"sin_dato","autogenerado":null,"fuente":"","frontend_config":{},"timestamp_modificacion":"2022-09-16T21:47:24.776556"},{"id":2,"categoria":{"id":1,"nombre":"Fotografías aéreas","visibilidad":["cur3d","mapa_interactivo"]},"nombre":"Foto aérea CABA 1965","url":"https://vectortiles.usig.buenosaires.gob.ar/aereas/fotografias_aereas_1965_caba_3857/","anio":1965,"tipo":"","origen_datos":"sin_dato","autogenerado":null,"fuente":"","frontend_config":{},"timestamp_modificacion":"2022-09-16T21:50:10.521334"},{"id":3,"categoria":{"id":1,"nombre":"Fotografías aéreas","visibilidad":["cur3d","mapa_interactivo"]},"nombre":"Foto aérea CABA 1978","url":"https://vectortiles.usig.buenosaires.gob.ar/aereas/fotografias_aereas_1978_caba_3857/","anio":1978,"tipo":"","origen_datos":"sin_dato","autogenerado":null,"fuente":"","frontend_config":{},"timestamp_modificacion":"2022-09-16T21:51:17.211397"},{"id":4,"categoria":{"id":1,"nombre":"Fotografías aéreas","visibilidad":["cur3d","mapa_interactivo"]},"nombre":"Foto aérea CABA 2017","url":"https://vectortiles.usig.buenosaires.gob.ar/aereas/fotografias_aereas_2017_caba_3857/","anio":2017,"tipo":"","origen_datos":"sin_dato","autogenerado":null,"fuente":"","frontend_config":{},"timestamp_modificacion":"2022-09-16T21:52:17.428125"},{"id":5,"categoria":{"id":2,"nombre":"Imágenes satelitales","visibilidad":["cur3d","mapa_interactivo"]},"nombre":"Imagen satelital CABA 2004","url":"https://vectortiles.usig.buenosaires.gob.ar/satelitales/imagen_satelital_2004_caba_3857/","anio":2004,"tipo":"","origen_datos":"sin_dato","autogenerado":null,"fuente":"","frontend_config":{},"timestamp_modificacion":"2022-09-16T21:57:08.243587"},{"id":6,"categoria":{"id":2,"nombre":"Imágenes satelitales","visibilidad":["cur3d","mapa_interactivo"]},"nombre":"Imagen satelital CABA 2006","url":"https://vectortiles.usig.buenosaires.gob.ar/satelitales/imagen_satelital_2006_caba_3857/","anio":2006,"tipo":"","origen_datos":"sin_dato","autogenerado":null,"fuente":"","frontend_config":{},"timestamp_modificacion":"2022-09-16T21:58:03.284819"},{"id":7,"categoria":{"id":2,"nombre":"Imágenes satelitales","visibilidad":["cur3d","mapa_interactivo"]},"nombre":"Imagen satelital CABA 2008","url":"https://vectortiles.usig.buenosaires.gob.ar/satelitales/imagen_satelital_2008_caba_3857/","anio":2008,"tipo":"","origen_datos":"sin_dato","autogenerado":null,"fuente":"","frontend_config":{},"timestamp_modificacion":"2022-09-16T22:00:05.826981"},{"id":8,"categoria":{"id":2,"nombre":"Imágenes satelitales","visibilidad":["cur3d","mapa_interactivo"]},"nombre":"Imagen satelital CABA 2009","url":"https://vectortiles.usig.buenosaires.gob.ar/satelitales/imagen_satelital_2009_caba_3857/","anio":2009,"tipo":"","origen_datos":"sin_dato","autogenerado":null,"fuente":"","frontend_config":{},"timestamp_modificacion":"2022-09-16T22:01:19.365765"}]}}}